README.txt
bootstrap.py
buildout.cfg
defaults.cfg
parse2plone.py
setup.py
tests.py
docs/CONTRIBUTORS.txt
docs/HISTORY.txt
docs/LICENSE.txt
parse2plone.egg-info/PKG-INFO
parse2plone.egg-info/SOURCES.txt
parse2plone.egg-info/dependency_links.txt
parse2plone.egg-info/entry_points.txt
parse2plone.egg-info/requires.txt
parse2plone.egg-info/top_level.txt
sample/_illegal_file
sample/index.html
sample/2000/01/01/foo/index.html
sample/_illegal_directory/index.html
sample/about/index.html
sample/baz/index.html
sample/foo/index.html
sample2/sample/_illegal_file
sample2/sample/index.html
sample2/sample/2000/01/01/foo/index.html
sample2/sample/_illegal_directory/index.html
sample2/sample/about/index.html
sample2/sample/baz/index.html
sample2/sample/foo/index.html