Metadata-Version: 1.0
Name: parse2plone
Version: 0.9.8
Summary: Easily import static HTML websites into Plone.
Home-page: http://aclark4life.github.com/Parse2Plone
Author: Alex Clark
Author-email: aclark@aclark.net
License: UNKNOWN
Platform: UNKNOWN
Classifier: Framework :: Buildout
Classifier: Framework :: Plone
